kisters/network_store/model_library/water/__init__.py
kisters/network_store/model_library/water/controls.py
kisters/network_store/model_library/water/groups.py
kisters/network_store/model_library/water/links.py
kisters/network_store/model_library/water/nodes.py
kisters/network_store/model_library/water/py.typed
kisters.network_store.model_library.water-0.6.1.dist-info/METADATA
kisters.network_store.model_library.water-0.6.1.dist-info/WHEEL
kisters.network_store.model_library.water-0.6.1.dist-info/entry_points.txt
kisters.network_store.model_library.water-0.6.1.dist-info/top_level.txt
kisters.network_store.model_library.water-0.6.1.dist-info/RECORD
